ndispers/__init__.py
ndispers/_baseclass.py
ndispers/helper.py
ndispers/groups/__init__.py
ndispers/groups/_uniax_neg_32.py
ndispers/groups/_uniax_neg_3m.py
ndispers/media/__init__.py
ndispers/media/crystals/_CLBO.py
ndispers/media/crystals/_KBBF_Li2016.py
ndispers/media/crystals/_KDP.py
ndispers/media/crystals/_KTP.py
ndispers/media/crystals/_LB4.py
ndispers/media/crystals/_LBO_Castech.py
ndispers/media/crystals/_LBO_EKSMA.py
ndispers/media/crystals/_LBO_Ghosh1995.py
ndispers/media/crystals/_LBO_KK1994.py
ndispers/media/crystals/_LBO_KK2018.py
ndispers/media/crystals/_LBO_Newlight.py
ndispers/media/crystals/_RBBF_Chen2009.py
ndispers/media/crystals/_SLN_MgO_doped.py
ndispers/media/crystals/_SLT_MgO_doped.py
ndispers/media/crystals/__init__.py
ndispers/media/crystals/_alphaBBO.py
ndispers/media/crystals/_betaBBO_Eimerl1987.py
ndispers/media/crystals/_betaBBO_Ghosh1995.py
ndispers/media/crystals/_betaBBO_KK2010.py
ndispers/media/crystals/_betaBBO_Tamosauskas2018.py
ndispers/media/crystals/_calcite.py
ndispers/media/glasses/__init__.py
ndispers/media/glasses/_caf2.py
ndispers/media/glasses/_fusedsilica.py
ndispers/tests/test_KBBF.py
ndispers/tests/test_LBO.py
ndispers/tests/test_RBBF.py
ndispers/tests/test_betaBBO.py
ndispers-0.5.2.dist-info/METADATA
ndispers-0.5.2.dist-info/WHEEL
ndispers-0.5.2.dist-info/licenses/LICENSE
ndispers-0.5.2.dist-info/RECORD
