Metadata-Version: 2.4
Name: ndispers
Version: 0.5.2
Summary: Python package for calculating refractive index dispersion of various materials
Project-URL: Homepage, https://github.com/akihiko-shimura/ndispers
Author-email: Akihiko Shimura <akhksh@gmail.com>
License: MIT License
License-File: LICENSE
Classifier: License :: OSI Approved :: MIT License
Classifier: Operating System :: OS Independent
Classifier: Programming Language :: Python :: 3
Classifier: Programming Language :: Python :: 3.7
Classifier: Programming Language :: Python :: 3.8
Classifier: Programming Language :: Python :: 3.9
Classifier: Programming Language :: Python :: 3.10
Classifier: Programming Language :: Python :: 3.11
Requires-Dist: mpmath
Requires-Dist: numpy
Requires-Dist: scipy
Requires-Dist: sympy
